[
  {
    "palabra": "Angarillo",
    "definicion": "Persona delgada, flaca, individuo flaquísimo. “Ese pobre está del todo angarillo”."
  },
  {
    "palabra": "Ango",
    "definicion": "Tendón."
  },
  {
    "palabra": "Angurrioso",
    "definicion": "Individuo codicioso que quiere todo para él."
  },
  {
    "palabra": "Apa",
    "definicion": "Levantar. Hacer apa al nene es cargarlo."
  },
  {
    "palabra": "Aparente",
    "definicion": "Competente."
  },
  {
    "palabra": "Apiorado",
    "definicion": "Sinónimo de empeoró."
  },
  {
    "palabra": "Aporarse",
    "definicion": "Empeorarse."
  },
  {
    "palabra": "Aprete",
    "definicion": "Apriete."
  },
  {
    "palabra": "Aquisito",
    "definicion": "Aquí en este sitio."
  },
  {
    "palabra": "Arracacha",
    "definicion": "Planta de tubérculos comestibles."
  },
  {
    "palabra": "Arrancadas",
    "definicion": "Sopa de arepuelas."
  },
  {
    "palabra": "Arriado",
    "definicion": "Veloz. «El carro pasó arriadísimo»."
  },
  {
    "palabra": "Asedo",
    "definicion": "Alimento pasado, con mal sabor."
  },
  {
    "palabra": "Atarantado",
    "definicion": "Atolondrado, sin reflexión."
  },
  {
    "palabra": "Atatacas",
    "definicion": "Expresión quechua que significa asco, repugnancia, desdén o desprecio. Expresión para manifestar repudio."
  },
  {
    "palabra": "Atatay",
    "definicion": "Expresión quechua que significa asco, repugnancia, desdén o desprecio. Expresión para manifestar repudio."
  },
  {
    "palabra": "Atufado",
    "definicion": "Persona muy precipitada, afanosa, afanada."
  },
  {
    "palabra": "Auca",
    "definicion": "Niño que se muere sin haber sido bautizado."
  },
  {
    "palabra": "Aviejado",
    "definicion": "Niños con comportamiento de adultos."
  },
  {
    "palabra": "Avío",
    "definicion": "Ración de alimentos."
  },
  {
    "palabra": "Ayora",
    "definicion": "Exclamación producto del metaplasmo: ¡Ay!, ¿y Ahora?, Expresión usada para denotar rechazo a algún hecho."
  },
  {
    "palabra": "Azaroso",
    "definicion": "Antipático."
  },
  {
    "palabra": "Azarse",
    "definicion": "Avergonzarse."
  },
  {
    "palabra": "Bámbaro",
    "definicion": "Palabra para catalogar a una persona débil, miedosa, con tendencias homosexuales."
  },
  {
    "palabra": "Banderearse",
    "definicion": "Salir a pasear por la vía pública para ser visto."
  },
  {
    "palabra": "Barbacha",
    "definicion": "Musgo."
  },
  {
    "palabra": "Batido",
    "definicion": "Alfeñique de panela."
  },
  {
    "palabra": "Berraquillo",
    "definicion": "Cuero atado a una vara; látigo."
  },
  {
    "palabra": "Biche",
    "definicion": "Fruto Tierno."
  },
  {
    "palabra": "Biensísimo",
    "definicion": "Muy bien."
  },
  {
    "palabra": "Bleris",
    "definicion": "Neumático de balón."
  },
  {
    "palabra": "Bollo",
    "definicion": "Materia Fecal."
  },
  {
    "palabra": "Bonitico",
    "definicion": "Amoroso, lindo. Diminutivo que significa elegante, simpático, bien parecido. También se le llama así al pene."
  },
  {
    "palabra": "Boquiabierto",
    "definicion": "Cuy asado. Despistado."
  },
  {
    "palabra": "Boronda",
    "definicion": "Vuelta, paseo corto. \"Vamos a dar una boronda\"."
  },
  {
    "palabra": "Borrego",
    "definicion": "Cría de oveja."
  },
  {
    "palabra": "Botello",
    "definicion": "Botella llena de aguardiente."
  },
  {
    "palabra": "Breve",
    "definicion": "Expresión para decir rápido, temprano."
  },
  {
    "palabra": "Buenamente",
    "definicion": "En vano, Inútilmente."
  },
  {
    "palabra": "Cacana",
    "definicion": "Mierda."
  },
  {
    "palabra": "Cacha",
    "definicion": "Canica. También se les dice cachas a los amigos."
  },
  {
    "palabra": "Cachicado",
    "definicion": "Mordido, comido, deteriorado. Mal peluqueado."
  },
  {
    "palabra": "Cachicar",
    "definicion": "Morder, roer un hueso carnudo. \"Esperáraste, me cachico este hueso\"."
  },
  {
    "palabra": "Cachumbo",
    "definicion": "Rizo de pelo (Churo)."
  },
  {
    "palabra": "Cacorro",
    "definicion": "Homosexual."
  },
  {
    "palabra": "Caguinga",
    "definicion": "Cucharon de madera."
  },
  {
    "palabra": "Caibazo",
    "definicion": "Un doloroso golpe en el cabeza dado con los nudillos de los dedos y la mano cerrada."
  },
  {
    "palabra": "Caibo",
    "definicion": "Un doloroso golpe en el cabeza dado con los nudillos de los dedos y la mano cerrada."
  },
  {
    "palabra": "Caidizo",
    "definicion": "Techo artesanal. Dícese de una casa supremamente pobre."
  },
  {
    "palabra": "Calacuso",
    "definicion": "Parecido a caidizo. Un sitio de mala muerte."
  },
  {
    "palabra": "Callá, callá",
    "definicion": "No me digas."
  },
  {
    "palabra": "Calladito",
    "definicion": "En voz baja."
  },
  {
    "palabra": "Callamba",
    "definicion": "Hongo."
  },
  {
    "palabra": "Callana",
    "definicion": "Artefacto, cazoleta de barro cocido. Un gran plato hecho de barro para asar tortillas o tostar granos."
  },
  {
    "palabra": "Caminá",
    "definicion": "Vení."
  },
  {
    "palabra": "Canchero",
    "definicion": "De mucha experiencia."
  },
  {
    "palabra": "Candonga",
    "definicion": "Arete."
  },
  {
    "palabra": "Cangil",
    "definicion": "Clase de maíz."
  },
  {
    "palabra": "Capia",
    "definicion": "Cierto tipo de maíz que una vez tostado se denomina tostado."
  },
  {
    "palabra": "Caracho",
    "definicion": "Caramba."
  },
  {
    "palabra": "Cariargo",
    "definicion": "Cuy asado. Persona en estado de tristeza."
  },
  {
    "palabra": "Carisina",
    "definicion": "Mujer que no puede hacer los quehaceres de la casa, con poca habilidad doméstica. Mujer descuidada."
  },
  {
    "palabra": "Carura",
    "definicion": "Caro. ¡Qué carura de precios!"
  },
  {
    "palabra": "Caspa",
    "definicion": "Maíz en estado de madurez. Mazorca de maíz."
  },
  {
    "palabra": "Catiro",
    "definicion": "De cabello rubio."
  },
  {
    "palabra": "Cátulo",
    "definicion": "Hojas (envoltura) de maíz."
  },
  {
    "palabra": "Caucara",
    "definicion": "Carne de res."
  },
  {
    "palabra": "Chacla",
    "definicion": "Vara delgada. También se usa para decir que una persona es alta: “parece una chacla”"
  },
  {
    "palabra": "Chagra",
    "definicion": "Sementera, cultivo."
  },
  {
    "palabra": "Chalina",
    "definicion": "Chal."
  },
  {
    "palabra": "Chamba",
    "definicion": "Zanja."
  },
  {
    "palabra": "Champús",
    "definicion": "Bebida producida a base de maíz."
  },
  {
    "palabra": "Chancuco",
    "definicion": "Trampa en los exámenes. También es chapil (clase de licor)."
  },
  {
    "palabra": "Chandoso",
    "definicion": "Individuo con sarna. Con la piel lacerada. Piel de la cara con barros."
  },
  {
    "palabra": "Changar",
    "definicion": "Estrechar a otra persona con las piernas."
  },
  {
    "palabra": "Chapil",
    "definicion": "Clase de licor, aguardiente artesanal."
  },
  {
    "palabra": "Chaquilulo",
    "definicion": "Fruta pequeña comestible de color morado que crece de manera silvestre."
  },
  {
    "palabra": "Chaquira",
    "definicion": "Collar de mullos o cuentas pequeñas."
  },
  {
    "palabra": "Chara",
    "definicion": "Sopa a base de cebada."
  },
  {
    "palabra": "Charlón",
    "definicion": "Mentiroso, exagerado."
  },
  {
    "palabra": "Charosa",
    "definicion": "Chorreada."
  },
  {
    "palabra": "Chasco",
    "definicion": "Fracaso, vergüenza."
  },
  {
    "palabra": "Chay",
    "definicion": "Hace referencia de Achichay, que expresa frío."
  },
  {
    "palabra": "Chicanero",
    "definicion": "Mentiroso."
  },
  {
    "palabra": "Chichay",
    "definicion": "Expresión para manifestar frio."
  },
  {
    "palabra": "Chiche",
    "definicion": "Orina, pene."
  },
  {
    "palabra": "Chicuca",
    "definicion": "Empequeñecido. toda la plata se hizo chicuca (se perdió)."
  },
  {
    "palabra": "Chiguaco",
    "definicion": "Ave pequeña de color negro y pico amarillo."
  },
  {
    "palabra": "Chilacuán",
    "definicion": "Fruta pequeña parecida a la papaya, posible de consumir en forma de dulce."
  },
  {
    "palabra": "Chilletas",
    "definicion": "Llorón."
  },
  {
    "palabra": "Chilpa",
    "definicion": "Andrajo, ropa deteriorada."
  },
  {
    "palabra": "Chilposo",
    "definicion": "Andrajoso."
  },
  {
    "palabra": "Chiltado",
    "definicion": "Utensilio de porcelana descascarada por golpes."
  },
  {
    "palabra": "Chiltero",
    "definicion": "Persona chismosa. Grosero, vulgar."
  },
  {
    "palabra": "Chimba",
    "definicion": "Trenza."
  },
  {
    "palabra": "Chimbilaco",
    "definicion": "Murciélago."
  },
  {
    "palabra": "Chinchano",
    "definicion": "Oriundo de La Cruz (Nariño)."
  },
  {
    "palabra": "Chinchirimico",
    "definicion": "Gastar sin control."
  },
  {
    "palabra": "Chinga",
    "definicion": "Vulva."
  },
  {
    "palabra": "Chingo",
    "definicion": "Pene."
  },
  {
    "palabra": "Chirapiar",
    "definicion": "Lloviznar."
  },
  {
    "palabra": "Chirimbolo",
    "definicion": "Empleado, sirviente."
  },
  {
    "palabra": "Chirle",
    "definicion": "Aguado."
  },
  {
    "palabra": "Chiroso",
    "definicion": "Despeinado."
  },
  {
    "palabra": "Chistear",
    "definicion": "Hacer chistes."
  },
  {
    "palabra": "Choclo",
    "definicion": "Maíz tierno."
  },
  {
    "palabra": "Cholado",
    "definicion": "Helado."
  },
  {
    "palabra": "Chona",
    "definicion": "Boronda."
  },
  {
    "palabra": "Chubico",
    "definicion": "Ojo dañado. Tiene ojos chubicos."
  },
  {
    "palabra": "Chubiquió el ojo",
    "definicion": "Quedó muy sorprendido."
  },
  {
    "palabra": "Chucas",
    "definicion": "Expresión para decir ¡que caliente!"
  },
  {
    "palabra": "Chucha",
    "definicion": "Individuo cobarde. Débil."
  },
  {
    "palabra": "Chuchinga",
    "definicion": "Individuo cobarde. Débil."
  },
  {
    "palabra": "Chuchuco",
    "definicion": "Viejo, fruta arrugada."
  },
  {
    "palabra": "Chuletiado",
    "definicion": "Muerto."
  },
  {
    "palabra": "Chulla",
    "definicion": "Uno."
  },
  {
    "palabra": "Chumado",
    "definicion": "Persona ebria, borracha."
  },
  {
    "palabra": "Chumbo",
    "definicion": "Pavo."
  },
  {
    "palabra": "Chumemos",
    "definicion": "Bebamos licor."
  },
  {
    "palabra": "Chunchullo",
    "definicion": "Tripas de cerdo fritas."
  },
  {
    "palabra": "Chupar",
    "definicion": "Besar, tomar licor."
  },
  {
    "palabra": "Chupar llanta",
    "definicion": "Aprovecharse del que va adelante."
  },
  {
    "palabra": "Chupletiado",
    "definicion": "Desmayado."
  },
  {
    "palabra": "Chupó",
    "definicion": "Aguantó un regaño."
  },
  {
    "palabra": "Churiar",
    "definicion": "Dormirse, morirse. El Carlos tomó tanto que al fin churió."
  },
  {
    "palabra": "Churo",
    "definicion": "Bucle de cabello."
  },
  {
    "palabra": "Churoso",
    "definicion": "Crespo, de cabello ensortijado."
  },
  {
    "palabra": "Churria",
    "definicion": "Diarrea."
  },
  {
    "palabra": "Chuspe",
    "definicion": "Palo colgado en el centro de la cocina con los alimentos."
  },
  {
    "palabra": "Chuta",
    "definicion": "Sombrero."
  },
  {
    "palabra": "Chuy",
    "definicion": "Achichuy."
  },
  {
    "palabra": "Cimbrar",
    "definicion": "Vibrar."
  },
  {
    "palabra": "Clinudo",
    "definicion": "Persona con abundante cabello."
  },
  {
    "palabra": "Cochambroso",
    "definicion": "Mugroso."
  },
  {
    "palabra": "Comedido",
    "definicion": "Individuo con bastante disposición para realizar cualquier oficio o tarea."
  },
  {
    "palabra": "Conchavar",
    "definicion": "Ganar la voluntad de otro a favor de uno."
  },
  {
    "palabra": "Concho",
    "definicion": "Residuos de los fritos o de los brebajes que queda en el fondo."
  },
  {
    "palabra": "Cosiánfira",
    "definicion": "Algo que las señoras pretenden difícilmente mantener en secreto."
  },
  {
    "palabra": "Cucho",
    "definicion": "Rincón."
  },
  {
    "palabra": "Cueche",
    "definicion": "Arco iris."
  },
  {
    "palabra": "Cuesquiza",
    "definicion": "Jaleo, bronca."
  },
  {
    "palabra": "Cujaco",
    "definicion": "Nativo de Pupiales."
  },
  {
    "palabra": "Culillo",
    "definicion": "Miedo."
  },
  {
    "palabra": "Culimbo",
    "definicion": "Pobre."
  },
  {
    "palabra": "Cumbamba",
    "definicion": "Mentón inferior."
  },
  {
    "palabra": "Cunuco",
    "definicion": "Lugar, espacio (pieza) pequeño."
  },
  {
    "palabra": "Curco",
    "definicion": "Persona con joroba."
  },
  {
    "palabra": "Curí",
    "definicion": "Se le domina a un cuy macho."
  },
  {
    "palabra": "Curieles",
    "definicion": "Cuyes asados."
  },
  {
    "palabra": "Curuncho",
    "definicion": "Niño en camisa."
  },
  {
    "palabra": "Cururo",
    "definicion": "Ovillo de lana."
  },
  {
    "palabra": "Cuscungo",
    "definicion": "Animal silvestre. Feo."
  },
  {
    "palabra": "Cute",
    "definicion": "Herramienta de madera y hierro que se utiliza para cosechar papas."
  },
  {
    "palabra": "Cuy",
    "definicion": "Conejillo de indias."
  },
  {
    "palabra": "Cuzo",
    "definicion": "Gusano."
  },
  {
    "palabra": "Darasme",
    "definicion": "Haz el favor de... Darasme trayendo el pan."
  },
  {
    "palabra": "Derrandado",
    "definicion": "Roto, desconcido."
  },
  {
    "palabra": "Desaguado",
    "definicion": "Pálido, muy blanco."
  },
  {
    "palabra": "Descomedido",
    "definicion": "Persona antipática, que no obedece."
  },
  {
    "palabra": "Descujaríngado",
    "definicion": "Desbaratado."
  },
  {
    "palabra": "Desculado",
    "definicion": "Rapidísimo."
  },
  {
    "palabra": "Desgualangado",
    "definicion": "Desacomodado, informal, sin buena presentación, desaliñado, mal vestido."
  },
  {
    "palabra": "Desgualangarse",
    "definicion": "Caerse."
  },
  {
    "palabra": "Desinteria",
    "definicion": "Diarrea en lenguaje campesino."
  },
  {
    "palabra": "Desmierdado",
    "definicion": "Rapidísimo."
  },
  {
    "palabra": "Dinó",
    "definicion": "Si no."
  },
  {
    "palabra": "Disvariar",
    "definicion": "Decir cosas sin sentido."
  },
  {
    "palabra": "Donosa",
    "definicion": "Mujer bonita."
  },
  {
    "palabra": "Donoso",
    "definicion": "Individuo elegante."
  },
  {
    "palabra": "Echar quimba",
    "definicion": "Caminar."
  },
  {
    "palabra": "Echo churo",
    "definicion": "Dañado."
  },
  {
    "palabra": "Elay",
    "definicion": "Palabra que viene de ¡Hela ahí! o de la síncopa velay, exclamación muy española: Qué, cómo acá, ahí está ¡Eso es! ¿Lo ve Usted?, ¡ahí está!"
  },
  {
    "palabra": "Emparamado",
    "definicion": "Mojado."
  },
  {
    "palabra": "Empipado",
    "definicion": "Lleno de líquido."
  },
  {
    "palabra": "Empiparse",
    "definicion": "Persona con el estómago lleno o inflado de aire o líquido. Individuo con cólico."
  },
  {
    "palabra": "En par quiños",
    "definicion": "Ya mismo."
  },
  {
    "palabra": "En pura",
    "definicion": "Rapidísimo."
  },
  {
    "palabra": "Enchoclar",
    "definicion": "Ensartar, empatar."
  },
  {
    "palabra": "Enchumbado",
    "definicion": "Enojado."
  },
  {
    "palabra": "Enchurarse",
    "definicion": "Enrularse. Poner los rizos en orden, arreglarse."
  },
  {
    "palabra": "Endija",
    "definicion": "Rendija."
  },
  {
    "palabra": "Enjirpe",
    "definicion": "Obsequio, regalo."
  },
  {
    "palabra": "Enseñoritar",
    "definicion": "Para las gentes de la zona rural, el maíz está enseñoritando, cuando comienza a florecer."
  },
  {
    "palabra": "Entelerido",
    "definicion": "Entumido, tonto."
  },
  {
    "palabra": "Entreverado",
    "definicion": "Cosas bien mezcladas."
  },
  {
    "palabra": "Entumido",
    "definicion": "Persona triste, tímida, callada. Persona con mucho frio."
  },
  {
    "palabra": "Entumirse",
    "definicion": "Expresión utilizada para decir mucho frio."
  },
  {
    "palabra": "Esperarásé",
    "definicion": "Espere."
  },
  {
    "palabra": "Esperma",
    "definicion": "Vela, cera."
  },
  {
    "palabra": "Estampar",
    "definicion": "Pegar (Le estampó un puño en la cara)."
  },
  {
    "palabra": "Fierro",
    "definicion": "Hierro."
  },
  {
    "palabra": "Fijona",
    "definicion": "Criticona. La Ana Julia es bien fijona."
  },
  {
    "palabra": "Flamingo",
    "definicion": "Individuo alto, delgado, débil."
  },
  {
    "palabra": "Floriado",
    "definicion": "Esparcido, desordenado."
  },
  {
    "palabra": "Floriar",
    "definicion": "Esparcir."
  },
  {
    "palabra": "Foco",
    "definicion": "Bombillo."
  },
  {
    "palabra": "Follado",
    "definicion": "Clase de falda hecha de lana utilizada por las mujeres."
  },
  {
    "palabra": "Follón",
    "definicion": "Clase de falda hecha de lana utilizada por las mujeres."
  },
  {
    "palabra": "Forcha",
    "definicion": "Deliciosa bebida de cebada «enjuertecida»."
  },
  {
    "palabra": "Fritada",
    "definicion": "El plato de carne de cerdo frita, acompañado con otros alimentos (papa, choclo, ulluco)."
  },
  {
    "palabra": "Fuete",
    "definicion": "Látigo."
  },
  {
    "palabra": "Gáfaro",
    "definicion": "Audaz, de arranque, que no pierde ninguna. Viene de gafar o arrancar."
  },
  {
    "palabra": "Galembo",
    "definicion": "Gallinazo."
  },
  {
    "palabra": "Gomitar",
    "definicion": "Vomitar."
  },
  {
    "palabra": "Gorrear",
    "definicion": "Quiere todo gratis."
  },
  {
    "palabra": "Gradas",
    "definicion": "Escalera."
  },
  {
    "palabra": "Guácalas",
    "definicion": "Tatay."
  },
  {
    "palabra": "Guacho",
    "definicion": "Surco en la tierra. Camino mal trazado."
  },
  {
    "palabra": "Guagua",
    "definicion": "Niño(a) pequeño(a)."
  },
  {
    "palabra": "Guaiço",
    "definicion": "Término referido a un clima abrigado."
  },
  {
    "palabra": "Guaiçoso",
    "definicion": "Nacido en el guaico (En el cañón caliente del Guáitara)."
  },
  {
    "palabra": "Gualán",
    "definicion": "Caminado burdo de una persona."
  },
  {
    "palabra": "Gualanguear",
    "definicion": "Mover algo con fuerza."
  },
  {
    "palabra": "Gualca",
    "definicion": "Collar."
  },
  {
    "palabra": "Guambro",
    "definicion": "Joven en quechua. Hijo pequeño."
  },
  {
    "palabra": "Guanefia",
    "definicion": "Bambuco, baile típico del Departamento de Nariño (La Guaneña)."
  },
  {
    "palabra": "iguang",
    "definicion": "Atado de leña u otro artículo. Haz de leña, hierba o madera."
  },
  {
    "palabra": "Guargüero",
    "definicion": "Pescuezo."
  },
  {
    "palabra": "Guarme",
    "definicion": "Persona ágil, fuerte."
  },
  {
    "palabra": "Guasca",
    "definicion": "Hilo de fique trenzado."
  },
  {
    "palabra": "Guascazo",
    "definicion": "Puñetazo, golpe."
  },
  {
    "palabra": "Guato",
    "definicion": "Persona pequeña, de baja estatura."
  },
  {
    "palabra": "Güingo",
    "definicion": "Torcido."
  },
  {
    "palabra": "Gulumbia",
    "definicion": "Columpio."
  },
  {
    "palabra": "Hacer un champús",
    "definicion": "Revolver todo."
  },
  {
    "palabra": "Harneada",
    "definicion": "Sopa de maíz o cebada."
  },
  {
    "palabra": "Harniada",
    "definicion": "Sopa de maíz o cebada."
  },
  {
    "palabra": "Horasite",
    "definicion": "Expresión que significa temor, miedo."
  },
  {
    "palabra": "Hostigantísimo",
    "definicion": "Muy hostigante."
  },
  {
    "palabra": "Idiático",
    "definicion": "Terco, de ideas fijas."
  },
  {
    "palabra": "Indicción",
    "definicion": "Inyección."
  },
  {
    "palabra": "Jailai",
    "definicion": "Rico o de alcurnia social."
  },
  {
    "palabra": "Jailoso",
    "definicion": "Orgulloso, creído. Persona rica o de «buena» familia."
  },
  {
    "palabra": "Jecho",
    "definicion": "Fruto maduro, próximo a cosecharse."
  },
  {
    "palabra": "Jetón",
    "definicion": "Persona enojada o con labios gruesos."
  },
  {
    "palabra": "Jigra",
    "definicion": "Bolsa."
  },
  {
    "palabra": "Juagada",
    "definicion": "Nos traduce lavar.... Estoy juagando (lavando) la ropa."
  },
  {
    "palabra": "Jurgillas",
    "definicion": "Persona inquieta, molestosa, curiosa."
  },
  {
    "palabra": "Lamber",
    "definicion": "Lamer."
  },
  {
    "palabra": "Lambido",
    "definicion": "Un peinado que deja el cabello bien pegado a la cabeza."
  },
  {
    "palabra": "Lampareado",
    "definicion": "Totalmente salpicado de algo."
  },
  {
    "palabra": "Lapingacho",
    "definicion": "Tortilla de papa."
  },
  {
    "palabra": "Lempo",
    "definicion": "Hermosa(o). Esa mujer es un «lempo» de vieja."
  },
  {
    "palabra": "Lentico si no",
    "definicion": "Distraído."
  },
  {
    "palabra": "Ligero",
    "definicion": "Persona rápida, veloz."
  },
  {
    "palabra": "Limpo sucio",
    "definicion": "Muy sucio."
  },
  {
    "palabra": "Lisión",
    "definicion": "Fractura."
  },
  {
    "palabra": "Llamba",
    "definicion": "Se dice a la superficie de algo plano, gastado."
  },
  {
    "palabra": "Llambo",
    "definicion": "Liso."
  },
  {
    "palabra": "Lluspir",
    "definicion": "Resbalar, rodar."
  },
  {
    "palabra": "Lluspirse",
    "definicion": "Resbalarse."
  },
  {
    "palabra": "Lo cagaron",
    "definicion": "Le dieron duro."
  },
  {
    "palabra": "Machucar",
    "definicion": "Presionar, apretar."
  },
  {
    "palabra": "Maicena",
    "definicion": "Maíz pira reventado por acción del calor."
  },
  {
    "palabra": "Majar",
    "definicion": "Golpear."
  },
  {
    "palabra": "Maltón",
    "definicion": "Persona que inicia la edad adulta."
  },
  {
    "palabra": "Mamá señora",
    "definicion": "Abuela."
  },
  {
    "palabra": "Mamarón",
    "definicion": "Tipo grande, vago. De gran estatura, pero aniñado."
  },
  {
    "palabra": "Mamerto",
    "definicion": "Lento, tonto."
  },
  {
    "palabra": "Mandarse",
    "definicion": "Comer. Ayer me mandé una chuleta en Don Pancho."
  },
  {
    "palabra": "Mande",
    "definicion": "Expresión para decir qué."
  },
  {
    "palabra": "Manos de lana",
    "definicion": "Se le dice a una persona que deja caer algo de sus manos."
  },
  {
    "palabra": "Marcar",
    "definicion": "Cargar."
  },
  {
    "palabra": "Marimacho",
    "definicion": "Sinónimo de carisina y piscuda. Afín al mismo sexo."
  },
  {
    "palabra": "Marratico",
    "definicion": "Después, más tarde, luego."
  },
  {
    "palabra": "Marrato",
    "definicion": "Después, más tarde, luego."
  },
  {
    "palabra": "Martajar",
    "definicion": "Majar, remorder."
  },
  {
    "palabra": "Más después",
    "definicion": "Luego."
  },
  {
    "palabra": "Mate",
    "definicion": "Tasa hecha del calabazo."
  },
  {
    "palabra": "Me figuró",
    "definicion": "Me tocó."
  },
  {
    "palabra": "Meado el cueche",
    "definicion": "De poca inteligencia."
  },
  {
    "palabra": "Melga",
    "definicion": "Surco."
  },
  {
    "palabra": "Miedoso",
    "definicion": "Individuo cobarde."
  },
  {
    "palabra": "Minacuro",
    "definicion": "Luciérnaga."
  },
  {
    "palabra": "Modosita",
    "definicion": "De buenos modales."
  },
  {
    "palabra": "Mojoseado",
    "definicion": "Se refiere a cosas con moho, podrido, lleno de moho."
  },
  {
    "palabra": "Molo",
    "definicion": "Puré de papa, especialmente de la amarilla."
  },
  {
    "palabra": "Mordoré",
    "definicion": "Color morado, violeta."
  },
  {
    "palabra": "Morocho",
    "definicion": "Comida de maíz: mazamorra."
  },
  {
    "palabra": "Morrongo",
    "definicion": "Individuo hipócrita."
  },
  {
    "palabra": "Mortiño",
    "definicion": "Fruta silvestre."
  },
  {
    "palabra": "Mote",
    "definicion": "Maíz pelado, cocido y reventado."
  },
  {
    "palabra": "Muchar",
    "definicion": "Besar."
  },
  {
    "palabra": "Mucho",
    "definicion": "Beso en quechua."
  },
  {
    "palabra": "Mucho verano",
    "definicion": "Expresión, en tono gracioso, dirigida al dueño de la fiesta cuando escasea el trago."
  },
  {
    "palabra": "Mueco",
    "definicion": "Que le falta una o varias piezas dentales."
  },
  {
    "palabra": "Muelón",
    "definicion": "Con dientes grandes."
  },
  {
    "palabra": "Muérgano",
    "definicion": "Malo, desobediente."
  },
  {
    "palabra": "Mullo",
    "definicion": "Pepa seca pequeña usada para hacer chaquiras."
  },
  {
    "palabra": "Mullupa",
    "definicion": "Pequeña pieza de tela en que se guarda el dinero para llevarlo en medio de los senos."
  },
  {
    "palabra": "Munchira",
    "definicion": "Gusano lleno de pelos puntudos."
  },
  {
    "palabra": "Murga",
    "definicion": "Grupo musical."
  },
  {
    "palabra": "Naranjilla",
    "definicion": "Lulo."
  },
  {
    "palabra": "Nata",
    "definicion": "Moho producido por la humedad."
  },
  {
    "palabra": "Neto",
    "definicion": "Rectángulo dibujado en el suelo para jugar bolas."
  },
  {
    "palabra": "Ni fu ni fa",
    "definicion": "Nada."
  },
  {
    "palabra": "Niqua",
    "definicion": "Fruta silvestre. También se denomina a un gusano que nace en el estiércol de la vaca."
  },
  {
    "palabra": "Napa",
    "definicion": "O yapa, es el aumento que da la vendedora al cliente, muestra pequeña."
  },
  {
    "palabra": "Nervo",
    "definicion": "Pedazo de tendón en la carne."
  },
  {
    "palabra": "Nuco",
    "definicion": "Poco hábil."
  },
  {
    "palabra": "Oca",
    "definicion": "Tubérculo parecido al ulluco."
  },
  {
    "palabra": "Olloco",
    "definicion": "Un tubérculo pegajoso. Se le dice Olloco, Ulloco. Vienen en distintos colores, pero saben todos de igual manera."
  },
  {
    "palabra": "Orasite",
    "definicion": "Ahora si fue. \"Es lo que quedó\", \"ahora si te castigan\". La expresión es de temor."
  },
  {
    "palabra": "Patoniar",
    "definicion": "Caminar."
  },
  {
    "palabra": "Pauchado",
    "definicion": "Puesto boca abajo."
  },
  {
    "palabra": "Pay",
    "definicion": "Gracias."
  },
  {
    "palabra": "Pedigüeño",
    "definicion": "Que le gusta pedir."
  },
  {
    "palabra": "Pegarse",
    "definicion": "Mojarse, caerse, llorar, etc. Me pegué una mojada..."
  },
  {
    "palabra": "Pelirango",
    "definicion": "Que le gusta buscar pelea."
  },
  {
    "palabra": "Perol",
    "definicion": "Olla de metal."
  },
  {
    "palabra": "Pichingo",
    "definicion": "Pene."
  },
  {
    "palabra": "Pichinguiar",
    "definicion": "Hacer el amor."
  },
  {
    "palabra": "Pichirilo",
    "definicion": "Carro viejo."
  },
  {
    "palabra": "Pilche",
    "definicion": "Mate, vaso. Calabazo pequeño para servirse chicha o agua."
  },
  {
    "palabra": "Pipa",
    "definicion": "Barriga."
  },
  {
    "palabra": "Piruro",
    "definicion": "Objeto pequeño: parece un piruro."
  },
  {
    "palabra": "Pisarse",
    "definicion": "Irse. (Con su permiso, yo me piso)."
  },
  {
    "palabra": "Piscuda",
    "definicion": "Carisina."
  },
  {
    "palabra": "Pispilla",
    "definicion": "Mujer agraciada y activa."
  },
  {
    "palabra": "Pite",
    "definicion": "Pedazo."
  },
  {
    "palabra": "Poliada",
    "definicion": "Sopa de harina de maíz."
  },
  {
    "palabra": "Pondo",
    "definicion": "Olla grande."
  },
  {
    "palabra": "Probanga",
    "definicion": "Muestra, prueba de un manjar o golosina."
  },
  {
    "palabra": "Pucha",
    "definicion": "Nariz. Manga pucha: manga corta."
  },
  {
    "palabra": "Puendo",
    "definicion": "Caprichoso gentilicio aplicado de las personas del Ecuador."
  },
  {
    "palabra": "Pupo",
    "definicion": "Ombliqo."
  },
  {
    "palabra": "Puyoso",
    "definicion": "Persona de cabello liso."
  },
  {
    "palabra": "Querneja",
    "definicion": "Trenza de cabuya o del cabello."
  },
  {
    "palabra": "Quesillo",
    "definicion": "Cuajada."
  },
  {
    "palabra": "Quesqué",
    "definicion": "¿Qué es?"
  },
  {
    "palabra": "Quichala",
    "definicion": "Diarrea."
  },
  {
    "palabra": "Quichalero",
    "definicion": "Con diarrea."
  },
  {
    "palabra": "Quilico",
    "definicion": "Tonto. Angarillo."
  },
  {
    "palabra": "Quinde",
    "definicion": "Pájaro picaflor. Colibrí."
  },
  {
    "palabra": "Quiño",
    "definicion": "Golpe."
  },
  {
    "palabra": "Quique",
    "definicion": "Diente de leche."
  },
  {
    "palabra": "Quisindiquindi",
    "definicion": "Onomatopeya del acompañamiento de la guitarra para tonadas populares."
  },
  {
    "palabra": "Randar",
    "definicion": "Coser."
  },
  {
    "palabra": "Ratay",
    "definicion": "Palabra que significa miedo."
  },
  {
    "palabra": "Refajo",
    "definicion": "Enagua."
  },
  {
    "palabra": "Regresos",
    "definicion": "Vueltos."
  },
  {
    "palabra": "Reina claudia",
    "definicion": "Ciruela."
  },
  {
    "palabra": "Rejuntar",
    "definicion": "Juntar, agrupar, reunir."
  },
  {
    "palabra": "Rellena",
    "definicion": "Morcilla de cerdo."
  },
  {
    "palabra": "Remilgado",
    "definicion": "Persona molestosa para comer o aceptar algo."
  },
  {
    "palabra": "Repelusa",
    "definicion": "Fea, despeinada, despelucada, chozona."
  },
  {
    "palabra": "Repuestico",
    "definicion": "Mejorado."
  },
  {
    "palabra": "Resmillarse",
    "definicion": "Rasparse la piel por acción de una caída sobre suelo áspero."
  },
  {
    "palabra": "Reta",
    "definicion": "Sermón que da una persona enojada."
  },
  {
    "palabra": "Retranca",
    "definicion": "Correa que se sujeta a la silla del caballo."
  },
  {
    "palabra": "Rimerones",
    "definicion": "En gran cantidad."
  },
  {
    "palabra": "Rirre",
    "definicion": "Animal pequeño, miedoso. Insecto pequeño."
  },
  {
    "palabra": "Rompe",
    "definicion": "Ango duro."
  },
  {
    "palabra": "Rosas",
    "definicion": "Maicena, crispetas con sal."
  },
  {
    "palabra": "Roscon",
    "definicion": "Homosexual."
  },
  {
    "palabra": "Sacarase una foto",
    "definicion": "Tómese una foto."
  },
  {
    "palabra": "Sachacuy",
    "definicion": "Animal parecido al cuy."
  },
  {
    "palabra": "Salao",
    "definicion": "Persona de mala suerte."
  },
  {
    "palabra": "Sancochados",
    "definicion": "Dedos blancos y piel arrugada por la acción prolongada del agua. «Niños salgan de la piscina porque van a quedar sancochados»."
  },
  {
    "palabra": "Sango",
    "definicion": "Sopa de maíz con repollo."
  },
  {
    "palabra": "Saratano",
    "definicion": "Se denomina a los animales que tienen color negro con pintas o manchas blancas."
  },
  {
    "palabra": "Seco",
    "definicion": "Comida que se da después de la sopa. También se utiliza para decir que una persona es delgada, flaca."
  },
  {
    "palabra": "Sedita",
    "definicion": "Trompo que baila en un solo sitio «parece como dormido»."
  },
  {
    "palabra": "Sólido",
    "definicion": "Lugar solitario, callado."
  },
  {
    "palabra": "Sopón",
    "definicion": "Barrigón. Mal encarado, carón"
  },
  {
    "palabra": "Soreco",
    "definicion": "Sordo."
  },
  {
    "palabra": "Sullengo",
    "definicion": "Tela desgastada."
  },
  {
    "palabra": "Sungo",
    "definicion": "Corazón."
  },
  {
    "palabra": "Taita",
    "definicion": "Papá."
  },
  {
    "palabra": "Tangán",
    "definicion": "Armario colgado del techo que se utiliza para colocar o guardar alimentos, utensilios y bebidas."
  },
  {
    "palabra": "Tartango",
    "definicion": "Gangoso, tartamudo."
  },
  {
    "palabra": "Tatacallo",
    "definicion": "Babosa."
  },
  {
    "palabra": "Tatay",
    "definicion": "Expresión quechua que significa asco, repugnancia, desdén o desprecio. Expresión para manifestar repudio."
  },
  {
    "palabra": "Tener zungos",
    "definicion": "Ser valiente."
  },
  {
    "palabra": "Tilinga",
    "definicion": "Pedazo muy pequeño."
  },
  {
    "palabra": "Tiritingo",
    "definicion": "Enclenque, tembleque."
  },
  {
    "palabra": "Tisado",
    "definicion": "Tejido desgastado."
  },
  {
    "palabra": "Tisar",
    "definicion": "Dañar una tela: motas."
  },
  {
    "palabra": "Tolado",
    "definicion": "Lleno, completo, casi con exceso."
  },
  {
    "palabra": "Tóndolo",
    "definicion": "Torpe, tonto."
  },
  {
    "palabra": "Tontera",
    "definicion": "Sin importancia."
  },
  {
    "palabra": "Tranca",
    "definicion": "Soporte para asegurar las puertas."
  },
  {
    "palabra": "Trancar",
    "definicion": "Practicar. Trancarle al trago o al juego es practicar una u otra actividad o las dos."
  },
  {
    "palabra": "Tricito",
    "definicion": "Pedacito."
  },
  {
    "palabra": "Virolo",
    "definicion": "El vocablo significa bizco, pero en nuestro medio se aplica al tuerto, con poca capacidad para mirar, casi ciego."
  },
  {
    "palabra": "Virusa",
    "definicion": "Viruta."
  },
  {
    "palabra": "Volverse un champús",
    "definicion": "Enredarse, ensuciarse."
  },
  {
    "palabra": "Zampar",
    "definicion": "Tirar algo. Le zampó tremendo guascazo."
  },
  {
    "palabra": "Zapallo",
    "definicion": "Persona pequeña y gorda."
  },
  {
    "palabra": "Zarandelo",
    "definicion": "El trompo que baila como zarandeado. Que se mueve a un lado y a otro desordenadamente. «Me golpeé y quede zarandelo»"
  },
  {
    "palabra": "Zarandengue",
    "definicion": "Es propio del objeto moverse desordenadamente «Y eche pa’ca y eche pa’llá como trompo zarandengue», de la canción de Sol Barniz."
  },
  {
    "palabra": "Zumbar",
    "definicion": "Lanzar, arrojar. Empujar a alguien."
  },
  {
    "palabra": "Zumbo",
    "definicion": "Vacío."
  },
  {
    "palabra": "Zumbra",
    "definicion": "Lanzar."
  },
  {
    "palabra": "Zungos",
    "definicion": "Menudencias de los animales (estómago, hígado, bazo...)."
  },
  {
    "palabra": "Zurrón",
    "definicion": "Arrugado, viejo."
  }
]